simpleagents/__init__.py
simpleagents-0.0.1.dist-info/LICENSE
simpleagents-0.0.1.dist-info/METADATA
simpleagents-0.0.1.dist-info/WHEEL
simpleagents-0.0.1.dist-info/top_level.txt
simpleagents-0.0.1.dist-info/RECORD
