Metadata-Version: 2.2
Name: simpleagents
Version: 0.0.1
Summary: simpleagents
Author: abhishek
Project-URL: Homepage, https://github.com/abhishekkrthakur/simpleagents
Project-URL: Issues, https://github.com/abhishekkrthakur/simpleagents/issues
Keywords: simpleagents
Classifier: Development Status :: 5 - Production/Stable
Classifier: License :: OSI Approved :: Apache Software License
Classifier: Operating System :: OS Independent
Classifier: Programming Language :: Python :: 3.10
Classifier: Programming Language :: Python :: 3.11
Classifier: Topic :: Scientific/Engineering :: Artificial Intelligence
License-File: LICENSE
